simple_sarif/__init__.py
simple_sarif/sarif.py
simple_sarif-1.0.2.dist-info/LICENSE
simple_sarif-1.0.2.dist-info/METADATA
simple_sarif-1.0.2.dist-info/WHEEL
simple_sarif-1.0.2.dist-info/top_level.txt
simple_sarif-1.0.2.dist-info/RECORD
