Metadata-Version: 2.1
Name: simple-sarif
Version: 1.0.2
Summary: A library for creating and managing SARIF files.
Home-page: UNKNOWN
License: Apache License 2.0
Platform: UNKNOWN
Classifier: License :: OSI Approved :: Apache Software License
Classifier: Programming Language :: Python :: 3.8
Classifier: Programming Language :: Python :: 3.9
Classifier: Programming Language :: Python :: 3.10
Classifier: Programming Language :: Python :: 3.11
Classifier: Programming Language :: Python :: 3.12
Requires-Python: >=3.8
License-File: LICENSE
Requires-Dist: jsonschema (>=4.21.1)
